<?xml version="1.0" encoding="utf-8" ?>
<c2layout>
    <name>Main Menu</name>
    <sid>148780410296762</sid>
    <event-sheet>Menu sheet</event-sheet>
    <size>
        <width>1920</width>
        <height>1080</height>
    </size>
    <margins>
        <horizontal>500</horizontal>
        <vertical>500</vertical>
    </margins>
    <unbounded-scrolling>0</unbounded-scrolling>
    <layers>
        <layer name="Background" sid="590204271527002">
            <initially-visible>1</initially-visible>
            <background-color>255,255,255</background-color>
            <transparent>0</transparent>
            <parallax>
                <x>1</x>
                <y>1</y>
            </parallax>
            <zoom-rate>1</zoom-rate>
            <opacity>1</opacity>
            <force-own-texture>0</force-own-texture>
            <global>0</global>
            <use-render-cells>0</use-render-cells>
            <blend-mode>0</blend-mode>
            <effect-fallback>0</effect-fallback>
            <instances>
                <instance type="Sprite" uid="24">
                    <properties>
                        <initial-visibility>Visible</initial-visibility>
                        <initial-animation>Default</initial-animation>
                        <initial-frame>0</initial-frame>
                        <collisions>Enabled</collisions>
                    </properties>
                    <blend-mode>0</blend-mode>
                    <effect-fallback>0</effect-fallback>
                    <world>
                        <x>965</x>
                        <y>521</y>
                        <z>0</z>
                        <width>2048</width>
                        <height>1152</height>
                        <depth>0</depth>
                        <hotspotX>0.5</hotspotX>
                        <hotspotY>0.5</hotspotY>
                        <angle>0</angle>
                        <opacity>1</opacity>
                    </world>
                </instance>
                <instance type="Sprite2" uid="65">
                    <properties>
                        <initial-visibility>Visible</initial-visibility>
                        <initial-animation>Default</initial-animation>
                        <initial-frame>0</initial-frame>
                        <collisions>Enabled</collisions>
                    </properties>
                    <behavior-instances>
                        <behavior-instance type="Fade">
                            <properties>
                                <active-at-start>Yes</active-at-start>
                                <fade-in-time>1</fade-in-time>
                                <wait-time>0</wait-time>
                                <fade-out-time>0</fade-out-time>
                                <destroy>After fade out</destroy>
                            </properties>
                        </behavior-instance>
                    </behavior-instances>
                    <blend-mode>0</blend-mode>
                    <effect-fallback>0</effect-fallback>
                    <world>
                        <x>1718</x>
                        <y>910</y>
                        <z>0</z>
                        <width>256</width>
                        <height>334</height>
                        <depth>0</depth>
                        <hotspotX>0.5</hotspotX>
                        <hotspotY>0.5</hotspotY>
                        <angle>0</angle>
                        <opacity>1</opacity>
                    </world>
                </instance>
                <instance type="Sprite4" uid="66">
                    <properties>
                        <initial-visibility>Visible</initial-visibility>
                        <initial-animation>Default</initial-animation>
                        <initial-frame>0</initial-frame>
                        <collisions>Enabled</collisions>
                    </properties>
                    <behavior-instances>
                        <behavior-instance type="Fade">
                            <properties>
                                <active-at-start>Yes</active-at-start>
                                <fade-in-time>1</fade-in-time>
                                <wait-time>0</wait-time>
                                <fade-out-time>0</fade-out-time>
                                <destroy>After fade out</destroy>
                            </properties>
                        </behavior-instance>
                    </behavior-instances>
                    <blend-mode>0</blend-mode>
                    <effect-fallback>0</effect-fallback>
                    <world>
                        <x>985</x>
                        <y>232</y>
                        <z>0</z>
                        <width>960</width>
                        <height>540</height>
                        <depth>0</depth>
                        <hotspotX>0.5</hotspotX>
                        <hotspotY>0.5</hotspotY>
                        <angle>0</angle>
                        <opacity>1</opacity>
                    </world>
                </instance>
                <instance type="Source" uid="67">
                    <properties>
                        <initial-visibility>Visible</initial-visibility>
                        <initial-animation>Default</initial-animation>
                        <initial-frame>0</initial-frame>
                        <collisions>Enabled</collisions>
                    </properties>
                    <blend-mode>0</blend-mode>
                    <effect-fallback>0</effect-fallback>
                    <world>
                        <x>90</x>
                        <y>1043</y>
                        <z>0</z>
                        <width>156</width>
                        <height>44</height>
                        <depth>0</depth>
                        <hotspotX>0.5</hotspotX>
                        <hotspotY>0.5</hotspotY>
                        <angle>0</angle>
                        <opacity>1</opacity>
                    </world>
                </instance>
                <instance type="Sources_button" uid="70">
                    <properties>
                        <initial-visibility>Visible</initial-visibility>
                        <initial-animation>Default</initial-animation>
                        <initial-frame>0</initial-frame>
                        <collisions>Enabled</collisions>
                    </properties>
                    <blend-mode>0</blend-mode>
                    <effect-fallback>0</effect-fallback>
                    <world>
                        <x>748</x>
                        <y>1149</y>
                        <z>0</z>
                        <width>222.315933228</width>
                        <height>45.026012421</height>
                        <depth>0</depth>
                        <hotspotX>0.949367106</hotspotX>
                        <hotspotY>2.84375</hotspotY>
                        <angle>0</angle>
                        <opacity>1</opacity>
                    </world>
                </instance>
            </instances>
            <effects />
        </layer>
        <layer name="UI" sid="724203828270206">
            <initially-visible>1</initially-visible>
            <background-color>255,255,255</background-color>
            <transparent>1</transparent>
            <parallax>
                <x>1</x>
                <y>1</y>
            </parallax>
            <zoom-rate>1</zoom-rate>
            <opacity>1</opacity>
            <force-own-texture>0</force-own-texture>
            <global>0</global>
            <use-render-cells>0</use-render-cells>
            <blend-mode>0</blend-mode>
            <effect-fallback>0</effect-fallback>
            <instances>
                <instance type="Stick" uid="7">
                    <properties>
                        <initial-visibility>Visible</initial-visibility>
                        <initial-animation>Default</initial-animation>
                        <initial-frame>0</initial-frame>
                        <collisions>Enabled</collisions>
                    </properties>
                    <behavior-instances>
                        <behavior-instance type="Bullet">
                            <properties>
                                <speed>800</speed>
                                <acceleration>0</acceleration>
                                <gravity>0</gravity>
                                <bounce-off-solids>No</bounce-off-solids>
                                <set-angle>No</set-angle>
                                <initial-state>Disabled</initial-state>
                            </properties>
                        </behavior-instance>
                        <behavior-instance type="Fade">
                            <properties>
                                <active-at-start>Yes</active-at-start>
                                <fade-in-time>1</fade-in-time>
                                <wait-time>0</wait-time>
                                <fade-out-time>0</fade-out-time>
                                <destroy>After fade out</destroy>
                            </properties>
                        </behavior-instance>
                    </behavior-instances>
                    <blend-mode>0</blend-mode>
                    <effect-fallback>0</effect-fallback>
                    <world>
                        <x>960</x>
                        <y>808.176391602</y>
                        <z>0</z>
                        <width>57.982406616</width>
                        <height>655.647216797</height>
                        <depth>0</depth>
                        <hotspotX>0.5</hotspotX>
                        <hotspotY>0.5</hotspotY>
                        <angle>0</angle>
                        <opacity>1</opacity>
                    </world>
                </instance>
                <instance type="StartButtonNew" uid="2">
                    <properties>
                        <initial-visibility>Visible</initial-visibility>
                        <initial-animation>Default</initial-animation>
                        <initial-frame>0</initial-frame>
                        <collisions>Enabled</collisions>
                    </properties>
                    <behavior-instances>
                        <behavior-instance type="Bullet">
                            <properties>
                                <speed>800</speed>
                                <acceleration>0</acceleration>
                                <gravity>0</gravity>
                                <bounce-off-solids>No</bounce-off-solids>
                                <set-angle>No</set-angle>
                                <initial-state>Disabled</initial-state>
                            </properties>
                        </behavior-instance>
                        <behavior-instance type="Fade">
                            <properties>
                                <active-at-start>Yes</active-at-start>
                                <fade-in-time>1</fade-in-time>
                                <wait-time>0</wait-time>
                                <fade-out-time>0</fade-out-time>
                                <destroy>After fade out</destroy>
                            </properties>
                        </behavior-instance>
                    </behavior-instances>
                    <blend-mode>0</blend-mode>
                    <effect-fallback>0</effect-fallback>
                    <world>
                        <x>960</x>
                        <y>474</y>
                        <z>0</z>
                        <width>476</width>
                        <height>188</height>
                        <depth>0</depth>
                        <hotspotX>0.5</hotspotX>
                        <hotspotY>0.5</hotspotY>
                        <angle>0</angle>
                        <opacity>1</opacity>
                    </world>
                </instance>
                <instance type="OptionButton" uid="0">
                    <properties>
                        <initial-visibility>Visible</initial-visibility>
                        <initial-animation>Default</initial-animation>
                        <initial-frame>0</initial-frame>
                        <collisions>Enabled</collisions>
                    </properties>
                    <instance-variables>
                        <PopupOn>false</PopupOn>
                    </instance-variables>
                    <behavior-instances>
                        <behavior-instance type="Bullet">
                            <properties>
                                <speed>800</speed>
                                <acceleration>0</acceleration>
                                <gravity>0</gravity>
                                <bounce-off-solids>No</bounce-off-solids>
                                <set-angle>No</set-angle>
                                <initial-state>Disabled</initial-state>
                            </properties>
                        </behavior-instance>
                        <behavior-instance type="Fade">
                            <properties>
                                <active-at-start>Yes</active-at-start>
                                <fade-in-time>1</fade-in-time>
                                <wait-time>0</wait-time>
                                <fade-out-time>0</fade-out-time>
                                <destroy>After fade out</destroy>
                            </properties>
                        </behavior-instance>
                    </behavior-instances>
                    <blend-mode>0</blend-mode>
                    <effect-fallback>0</effect-fallback>
                    <world>
                        <x>960</x>
                        <y>711.821166992</y>
                        <z>0</z>
                        <width>291</width>
                        <height>138</height>
                        <depth>0</depth>
                        <hotspotX>0.5</hotspotX>
                        <hotspotY>0.5</hotspotY>
                        <angle>0</angle>
                        <opacity>1</opacity>
                    </world>
                </instance>
                <instance type="ExitButton" uid="1">
                    <properties>
                        <initial-visibility>Visible</initial-visibility>
                        <initial-animation>Default</initial-animation>
                        <initial-frame>0</initial-frame>
                        <collisions>Enabled</collisions>
                    </properties>
                    <behavior-instances>
                        <behavior-instance type="Bullet">
                            <properties>
                                <speed>800</speed>
                                <acceleration>0</acceleration>
                                <gravity>0</gravity>
                                <bounce-off-solids>No</bounce-off-solids>
                                <set-angle>No</set-angle>
                                <initial-state>Disabled</initial-state>
                            </properties>
                        </behavior-instance>
                        <behavior-instance type="Fade">
                            <properties>
                                <active-at-start>Yes</active-at-start>
                                <fade-in-time>1</fade-in-time>
                                <wait-time>0</wait-time>
                                <fade-out-time>0</fade-out-time>
                                <destroy>After fade out</destroy>
                            </properties>
                        </behavior-instance>
                    </behavior-instances>
                    <blend-mode>0</blend-mode>
                    <effect-fallback>0</effect-fallback>
                    <world>
                        <x>960</x>
                        <y>901</y>
                        <z>0</z>
                        <width>188</width>
                        <height>112</height>
                        <depth>0</depth>
                        <hotspotX>0.5</hotspotX>
                        <hotspotY>0.5</hotspotY>
                        <angle>0</angle>
                        <opacity>1</opacity>
                    </world>
                </instance>
                <instance type="Sprite7" uid="68">
                    <properties>
                        <initial-visibility>Visible</initial-visibility>
                        <initial-animation>Default</initial-animation>
                        <initial-frame>0</initial-frame>
                        <collisions>Enabled</collisions>
                    </properties>
                    <instance-variables>
                        <AboutOn>false</AboutOn>
                    </instance-variables>
                    <blend-mode>0</blend-mode>
                    <effect-fallback>0</effect-fallback>
                    <world>
                        <x>9</x>
                        <y>1101</y>
                        <z>0</z>
                        <width>1920</width>
                        <height>1080</height>
                        <depth>0</depth>
                        <hotspotX>0</hotspotX>
                        <hotspotY>0</hotspotY>
                        <angle>0</angle>
                        <opacity>1</opacity>
                    </world>
                </instance>
                <instance type="Sprite8" uid="69">
                    <properties>
                        <initial-visibility>Visible</initial-visibility>
                        <initial-animation>Default</initial-animation>
                        <initial-frame>0</initial-frame>
                        <collisions>Enabled</collisions>
                    </properties>
                    <blend-mode>0</blend-mode>
                    <effect-fallback>0</effect-fallback>
                    <world>
                        <x>2212</x>
                        <y>-83</y>
                        <z>0</z>
                        <width>40</width>
                        <height>40</height>
                        <depth>0</depth>
                        <hotspotX>0.5</hotspotX>
                        <hotspotY>0.5</hotspotY>
                        <angle>0</angle>
                        <opacity>1</opacity>
                    </world>
                </instance>
                <instance type="Source_page" uid="71">
                    <properties>
                        <initial-visibility>Visible</initial-visibility>
                        <initial-animation>Default</initial-animation>
                        <initial-frame>0</initial-frame>
                        <collisions>Enabled</collisions>
                    </properties>
                    <blend-mode>0</blend-mode>
                    <effect-fallback>0</effect-fallback>
                    <world>
                        <x>2089</x>
                        <y>93</y>
                        <z>0</z>
                        <width>1926</width>
                        <height>1080</height>
                        <depth>0</depth>
                        <hotspotX>0</hotspotX>
                        <hotspotY>0</hotspotY>
                        <angle>0</angle>
                        <opacity>1</opacity>
                    </world>
                </instance>
                <instance type="X" uid="72">
                    <properties>
                        <initial-visibility>Visible</initial-visibility>
                        <initial-animation>Default</initial-animation>
                        <initial-frame>0</initial-frame>
                        <collisions>Enabled</collisions>
                    </properties>
                    <blend-mode>0</blend-mode>
                    <effect-fallback>0</effect-fallback>
                    <world>
                        <x>2136</x>
                        <y>134</y>
                        <z>0</z>
                        <width>40</width>
                        <height>40</height>
                        <depth>0</depth>
                        <hotspotX>0.5</hotspotX>
                        <hotspotY>0.5</hotspotY>
                        <angle>0</angle>
                        <opacity>1</opacity>
                    </world>
                </instance>
            </instances>
            <effects />
        </layer>
        <layer name="Layer 0" sid="297210597192535">
            <initially-visible>0</initially-visible>
            <background-color>255,255,255</background-color>
            <transparent>1</transparent>
            <parallax>
                <x>1</x>
                <y>1</y>
            </parallax>
            <zoom-rate>1</zoom-rate>
            <opacity>1</opacity>
            <force-own-texture>0</force-own-texture>
            <global>0</global>
            <use-render-cells>0</use-render-cells>
            <blend-mode>0</blend-mode>
            <effect-fallback>0</effect-fallback>
            <instances>
                <instance type="PopupBG" uid="5">
                    <properties>
                        <initial-visibility>Visible</initial-visibility>
                        <initial-animation>Default</initial-animation>
                        <initial-frame>0</initial-frame>
                        <collisions>Enabled</collisions>
                    </properties>
                    <behavior-instances>
                        <behavior-instance type="Fade">
                            <properties>
                                <active-at-start>No</active-at-start>
                                <fade-in-time>1</fade-in-time>
                                <wait-time>0</wait-time>
                                <fade-out-time>0</fade-out-time>
                                <destroy>No</destroy>
                            </properties>
                        </behavior-instance>
                    </behavior-instances>
                    <blend-mode>0</blend-mode>
                    <effect-fallback>0</effect-fallback>
                    <world>
                        <x>1870</x>
                        <y>-294</y>
                        <z>0</z>
                        <width>761</width>
                        <height>334</height>
                        <depth>0</depth>
                        <hotspotX>0.5</hotspotX>
                        <hotspotY>0.5</hotspotY>
                        <angle>0</angle>
                        <opacity>1</opacity>
                    </world>
                </instance>
                <instance type="MusicIcon" uid="9">
                    <properties>
                        <initial-visibility>Visible</initial-visibility>
                        <initial-animation>Default</initial-animation>
                        <initial-frame>0</initial-frame>
                        <collisions>Enabled</collisions>
                    </properties>
                    <behavior-instances>
                        <behavior-instance type="Fade">
                            <properties>
                                <active-at-start>No</active-at-start>
                                <fade-in-time>1</fade-in-time>
                                <wait-time>0</wait-time>
                                <fade-out-time>0</fade-out-time>
                                <destroy>No</destroy>
                            </properties>
                        </behavior-instance>
                    </behavior-instances>
                    <blend-mode>0</blend-mode>
                    <effect-fallback>0</effect-fallback>
                    <world>
                        <x>1691</x>
                        <y>-294</y>
                        <z>0</z>
                        <width>256</width>
                        <height>262.243988037</height>
                        <depth>0</depth>
                        <hotspotX>0.5</hotspotX>
                        <hotspotY>0.5</hotspotY>
                        <angle>0</angle>
                        <opacity>1</opacity>
                    </world>
                </instance>
                <instance type="SFXIcon" uid="10">
                    <properties>
                        <initial-visibility>Visible</initial-visibility>
                        <initial-animation>Default</initial-animation>
                        <initial-frame>0</initial-frame>
                        <collisions>Enabled</collisions>
                    </properties>
                    <behavior-instances>
                        <behavior-instance type="Fade">
                            <properties>
                                <active-at-start>No</active-at-start>
                                <fade-in-time>1</fade-in-time>
                                <wait-time>0</wait-time>
                                <fade-out-time>0</fade-out-time>
                                <destroy>No</destroy>
                            </properties>
                        </behavior-instance>
                    </behavior-instances>
                    <blend-mode>0</blend-mode>
                    <effect-fallback>0</effect-fallback>
                    <world>
                        <x>2052</x>
                        <y>-294</y>
                        <z>0</z>
                        <width>256</width>
                        <height>262.243988037</height>
                        <depth>0</depth>
                        <hotspotX>0.5</hotspotX>
                        <hotspotY>0.5</hotspotY>
                        <angle>0</angle>
                        <opacity>1</opacity>
                    </world>
                </instance>
                <instance type="MutedSFX" uid="3">
                    <properties>
                        <initial-visibility>Visible</initial-visibility>
                        <initial-animation>Default</initial-animation>
                        <initial-frame>0</initial-frame>
                        <collisions>Enabled</collisions>
                    </properties>
                    <behavior-instances>
                        <behavior-instance type="Fade">
                            <properties>
                                <active-at-start>No</active-at-start>
                                <fade-in-time>0.1</fade-in-time>
                                <wait-time>0</wait-time>
                                <fade-out-time>0</fade-out-time>
                                <destroy>No</destroy>
                            </properties>
                        </behavior-instance>
                    </behavior-instances>
                    <blend-mode>0</blend-mode>
                    <effect-fallback>0</effect-fallback>
                    <world>
                        <x>1146</x>
                        <y>-162</y>
                        <z>0</z>
                        <width>256</width>
                        <height>262.243988037</height>
                        <depth>0</depth>
                        <hotspotX>0.5</hotspotX>
                        <hotspotY>0.5</hotspotY>
                        <angle>0</angle>
                        <opacity>1</opacity>
                    </world>
                </instance>
                <instance type="MutedMusic" uid="11">
                    <properties>
                        <initial-visibility>Invisible</initial-visibility>
                        <initial-animation>Default</initial-animation>
                        <initial-frame>0</initial-frame>
                        <collisions>Enabled</collisions>
                    </properties>
                    <behavior-instances>
                        <behavior-instance type="Fade">
                            <properties>
                                <active-at-start>No</active-at-start>
                                <fade-in-time>0.1</fade-in-time>
                                <wait-time>0</wait-time>
                                <fade-out-time>0</fade-out-time>
                                <destroy>No</destroy>
                            </properties>
                        </behavior-instance>
                    </behavior-instances>
                    <blend-mode>0</blend-mode>
                    <effect-fallback>0</effect-fallback>
                    <world>
                        <x>766</x>
                        <y>-157</y>
                        <z>0</z>
                        <width>256</width>
                        <height>262.243896484</height>
                        <depth>0</depth>
                        <hotspotX>0.5</hotspotX>
                        <hotspotY>0.5</hotspotY>
                        <angle>0</angle>
                        <opacity>1</opacity>
                    </world>
                </instance>
                <instance type="xButton" uid="12">
                    <properties>
                        <initial-visibility>Visible</initial-visibility>
                        <initial-animation>Default</initial-animation>
                        <initial-frame>0</initial-frame>
                        <collisions>Enabled</collisions>
                    </properties>
                    <behavior-instances>
                        <behavior-instance type="Fade">
                            <properties>
                                <active-at-start>No</active-at-start>
                                <fade-in-time>1</fade-in-time>
                                <wait-time>0</wait-time>
                                <fade-out-time>0</fade-out-time>
                                <destroy>No</destroy>
                            </properties>
                        </behavior-instance>
                    </behavior-instances>
                    <blend-mode>0</blend-mode>
                    <effect-fallback>0</effect-fallback>
                    <world>
                        <x>2193.792236328</x>
                        <y>-406.679168701</y>
                        <z>0</z>
                        <width>36.258621216</width>
                        <height>36.258621216</height>
                        <depth>0</depth>
                        <hotspotX>0.5</hotspotX>
                        <hotspotY>0.5</hotspotY>
                        <angle>0</angle>
                        <opacity>1</opacity>
                    </world>
                </instance>
            </instances>
            <effects />
        </layer>
    </layers>
    <nonworld-instances />
    <effects />
</c2layout>
